README.md
setup.cfg
setup.py
update_check/__init__.py
update_check/main.py
update_check.egg-info/PKG-INFO
update_check.egg-info/SOURCES.txt
update_check.egg-info/dependency_links.txt
update_check.egg-info/requires.txt
update_check.egg-info/top_level.txt