Metadata-Version: 2.1
Name: update-check
Version: 0.0.6
Summary: Package to update the end-users copy of your file to the latest version
Home-page: https://github.com/TabulateJarl8/update_check
Author: Tabulate
Author-email: tabulatejarl8@gmail.com
License: UNKNOWN
Platform: UNKNOWN
Classifier: Programming Language :: Python :: 3
Classifier: License :: OSI Approved :: MIT License
Classifier: Operating System :: OS Independent
Requires-Python: >=3.6
